s3tokenizer/__init__.py
s3tokenizer/cli.py
s3tokenizer/model.py
s3tokenizer/model_v2.py
s3tokenizer/model_v3.py
s3tokenizer/utils.py
s3tokenizer/assets/BAC009S0764W0121.wav
s3tokenizer/assets/BAC009S0764W0122.wav
s3tokenizer/assets/mel_filters.npz
s3tokenizer-0.3.0.dist-info/LICENSE
s3tokenizer-0.3.0.dist-info/METADATA
s3tokenizer-0.3.0.dist-info/WHEEL
s3tokenizer-0.3.0.dist-info/entry_points.txt
s3tokenizer-0.3.0.dist-info/top_level.txt
s3tokenizer-0.3.0.dist-info/RECORD
