Metadata-Version: 2.1
Name: s3tokenizer
Version: 0.3.0
Summary: Reverse Engineering of Supervised Semantic Speech Tokenizer (S3Tokenizer) proposed in CosyVoice
Home-page: https://github.com/xingchensong/S3Tokenizer
Author: xingchensong
License: Apache2.0
Classifier: Programming Language :: Python :: 3
Classifier: Operating System :: OS Independent
Classifier: Topic :: Scientific/Engineering
Requires-Python: >=3.8
License-File: LICENSE
Requires-Dist: pre-commit
Requires-Dist: numpy
Requires-Dist: torch
Requires-Dist: onnx
Requires-Dist: tqdm
Requires-Dist: torchaudio
Requires-Dist: einops
Provides-Extra: dev
Requires-Dist: pytest ; extra == 'dev'
Requires-Dist: scipy ; extra == 'dev'
Requires-Dist: black ; extra == 'dev'
Requires-Dist: flake8 ; extra == 'dev'
Requires-Dist: isort ; extra == 'dev'
